ftlbgp/__init__.py
ftlbgp/__main__.py
ftlbgp/parser.py
ftlbgp/version.py
ftlbgp/data/__init__.py
ftlbgp/data/const.py
ftlbgp/data/util.py
ftlbgp/data/lgl/__init__.py
ftlbgp/data/lgl/table.py
ftlbgp/data/lgl/unpack.py
ftlbgp/data/mrt/__init__.py
ftlbgp/data/mrt/unpack.py
ftlbgp/data/mrt/bgp/__init__.py
ftlbgp/data/mrt/bgp/attr.py
ftlbgp/data/mrt/bgp/const.py
ftlbgp/data/mrt/bgp/msg.py
ftlbgp/data/mrt/bgp/nlri.py
ftlbgp/data/mrt/entry/__init__.py
ftlbgp/data/mrt/entry/bgp.py
ftlbgp/data/mrt/entry/bgp4mp.py
ftlbgp/data/mrt/entry/const.py
ftlbgp/data/mrt/entry/td.py
ftlbgp/data/mrt/entry/tdv2.py
ftlbgp/model/__init__.py
ftlbgp/model/attr.py
ftlbgp/model/const.py
ftlbgp/model/error.py
ftlbgp/model/record.py
ftlbgp/model/stats.py
ftlbgp/model/util.py
ftlbgp-1.0.5.dist-info/METADATA
ftlbgp-1.0.5.dist-info/WHEEL
ftlbgp-1.0.5.dist-info/RECORD
