Metadata-Version: 2.4
Name: ftlbgp
Version: 1.0.5
Summary: A Python parser for BGP data in MRT or looking glass format
Project-URL: Homepage, https://github.com/leitwert-net/ftlbgp
Project-URL: Issues, https://github.com/leitwert-net/ftlbgp/issues
Author-email: Johann SCHLAMP <schlamp@leitwert.net>
Keywords: BGP,MRT,parser
Classifier: Development Status :: 5 - Production/Stable
Classifier: Intended Audience :: Developers
Classifier: Intended Audience :: Science/Research
Classifier: Intended Audience :: Telecommunications Industry
Classifier: License :: OSI Approved :: MIT License
Classifier: Operating System :: OS Independent
Classifier: Programming Language :: Python :: 3
Classifier: Programming Language :: Python :: Implementation :: CPython
Classifier: Programming Language :: Python :: Implementation :: PyPy
Requires-Python: >=3.6
